{
  "news": [
    {
      "title": "Top 12 business process management certifications for 2025",
      "date": "2025-01-09 12:00:00",
      "generated_at": "2025-01-10 00:05:30",
      "meme_files": [
        "meme_20250110_000513_1.jpg",
        "meme_20250110_000514_2.jpg",
        "meme_20250110_000516_3.jpg",
        "meme_20250110_000517_4.jpg",
        "meme_20250110_000518_5.jpg",
        "meme_20250110_000519_6.jpg",
        "meme_20250110_000520_7.jpg",
        "meme_20250110_000521_8.jpg",
        "meme_20250110_000522_9.jpg",
        "meme_20250110_000523_10.jpg",
        "meme_20250110_000524_11.jpg",
        "meme_20250110_000525_12.jpg",
        "meme_20250110_000526_13.jpg",
        "meme_20250110_000528_14.jpg",
        "meme_20250110_000529_15.jpg",
        "meme_20250110_000530_16.jpg"
      ]
    },
    {
      "title": "How Richard DiMarchi Revolutionized Diabetes Treatment",
      "date": "2025-01-09 12:00:23",
      "generated_at": "2025-01-10 00:03:52",
      "meme_files": [
        "meme_20250110_000336_1.jpg",
        "meme_20250110_000337_2.jpg",
        "meme_20250110_000338_3.jpg",
        "meme_20250110_000339_4.jpg",
        "meme_20250110_000341_5.jpg",
        "meme_20250110_000342_6.jpg",
        "meme_20250110_000343_7.jpg",
        "meme_20250110_000344_8.jpg",
        "meme_20250110_000345_9.jpg",
        "meme_20250110_000346_10.jpg",
        "meme_20250110_000347_11.jpg",
        "meme_20250110_000348_12.jpg",
        "meme_20250110_000349_13.jpg",
        "meme_20250110_000350_14.jpg",
        "meme_20250110_000351_15.jpg",
        "meme_20250110_000352_16.jpg"
      ]
    },
    {
      "title": "Poco has announced the coolest, geekiest phone of CES 2025",
      "date": "2025-01-09 12:00:59",
      "generated_at": "2025-01-10 00:03:25",
      "meme_files": [
        "meme_20250110_000309_1.jpg",
        "meme_20250110_000310_2.jpg",
        "meme_20250110_000311_3.jpg",
        "meme_20250110_000312_4.jpg",
        "meme_20250110_000313_5.jpg",
        "meme_20250110_000314_6.jpg",
        "meme_20250110_000315_7.jpg",
        "meme_20250110_000316_8.jpg",
        "meme_20250110_000317_9.jpg",
        "meme_20250110_000318_10.jpg",
        "meme_20250110_000319_11.jpg",
        "meme_20250110_000321_12.jpg",
        "meme_20250110_000322_13.jpg",
        "meme_20250110_000323_14.jpg",
        "meme_20250110_000324_15.jpg",
        "meme_20250110_000325_16.jpg"
      ]
    },
    {
      "title": "Top SAP S/4HANA alternatives to add to your ERP shortlist",
      "date": "2025-01-09 12:01:00",
      "generated_at": "2025-01-10 00:02:58",
      "meme_files": [
        "meme_20250110_000242_1.jpg",
        "meme_20250110_000243_2.jpg",
        "meme_20250110_000244_3.jpg",
        "meme_20250110_000245_4.jpg",
        "meme_20250110_000247_5.jpg",
        "meme_20250110_000247_6.jpg",
        "meme_20250110_000248_7.jpg",
        "meme_20250110_000249_8.jpg",
        "meme_20250110_000250_9.jpg",
        "meme_20250110_000251_10.jpg",
        "meme_20250110_000252_11.jpg",
        "meme_20250110_000253_12.jpg",
        "meme_20250110_000254_13.jpg",
        "meme_20250110_000255_14.jpg",
        "meme_20250110_000256_15.jpg",
        "meme_20250110_000258_16.jpg"
      ]
    },
    {
      "title": "YEEDI S14 PLUS Wins Indoor Cleaning Technology Innovation Gold Award: Redefining Home Cleaning with Excellence in Innovation",
      "date": "2025-01-09 00:00:00",
      "generated_at": "2025-01-09 12:04:36",
      "meme_files": [
        "meme_20250109_120421_1.jpg",
        "meme_20250109_120422_2.jpg",
        "meme_20250109_120423_3.jpg",
        "meme_20250109_120424_4.jpg",
        "meme_20250109_120425_5.jpg",
        "meme_20250109_120426_6.jpg",
        "meme_20250109_120427_7.jpg",
        "meme_20250109_120428_8.jpg",
        "meme_20250109_120429_9.jpg",
        "meme_20250109_120430_10.jpg",
        "meme_20250109_120431_11.jpg",
        "meme_20250109_120432_12.jpg",
        "meme_20250109_120433_13.jpg",
        "meme_20250109_120434_14.jpg",
        "meme_20250109_120435_15.jpg",
        "meme_20250109_120436_16.jpg"
      ]
    },
    {
      "title": "RISC-V Breakthrough: SpacemiT Develops Server CPU Chip V100 for Next-Generation AI Applications",
      "date": "2025-01-09 00:00:00",
      "generated_at": "2025-01-09 12:04:10",
      "meme_files": [
        "meme_20250109_120356_1.jpg",
        "meme_20250109_120357_2.jpg",
        "meme_20250109_120357_3.jpg",
        "meme_20250109_120359_4.jpg",
        "meme_20250109_120359_5.jpg",
        "meme_20250109_120400_6.jpg",
        "meme_20250109_120401_7.jpg",
        "meme_20250109_120402_8.jpg",
        "meme_20250109_120403_9.jpg",
        "meme_20250109_120404_10.jpg",
        "meme_20250109_120405_11.jpg",
        "meme_20250109_120406_12.jpg",
        "meme_20250109_120407_13.jpg",
        "meme_20250109_120408_14.jpg",
        "meme_20250109_120409_15.jpg",
        "meme_20250109_120410_16.jpg"
      ]
    },
    {
      "title": "Toyota Is Building a Bjarke Ingels\u2013Designed City in Japan",
      "date": "2025-01-09 00:00:00",
      "generated_at": "2025-01-09 12:03:36",
      "meme_files": [
        "meme_20250109_120320_1.jpg",
        "meme_20250109_120321_2.jpg",
        "meme_20250109_120322_3.jpg",
        "meme_20250109_120323_4.jpg",
        "meme_20250109_120324_5.jpg",
        "meme_20250109_120326_6.jpg",
        "meme_20250109_120327_7.jpg",
        "meme_20250109_120328_8.jpg",
        "meme_20250109_120329_9.jpg",
        "meme_20250109_120330_10.jpg",
        "meme_20250109_120331_11.jpg",
        "meme_20250109_120332_12.jpg",
        "meme_20250109_120333_13.jpg",
        "meme_20250109_120335_14.jpg",
        "meme_20250109_120335_15.jpg",
        "meme_20250109_120336_16.jpg"
      ]
    },
    {
      "title": "Millions head online at 6am, 7am and 8am as alarms go off, data shows",
      "date": "2025-01-09 00:01:00",
      "generated_at": "2025-01-09 12:03:08",
      "meme_files": [
        "meme_20250109_120253_1.jpg",
        "meme_20250109_120254_2.jpg",
        "meme_20250109_120255_3.jpg",
        "meme_20250109_120256_4.jpg",
        "meme_20250109_120257_5.jpg",
        "meme_20250109_120258_6.jpg",
        "meme_20250109_120259_7.jpg",
        "meme_20250109_120300_8.jpg",
        "meme_20250109_120301_9.jpg",
        "meme_20250109_120302_10.jpg",
        "meme_20250109_120303_11.jpg",
        "meme_20250109_120304_12.jpg",
        "meme_20250109_120305_13.jpg",
        "meme_20250109_120306_14.jpg",
        "meme_20250109_120307_15.jpg",
        "meme_20250109_120308_16.jpg"
      ]
    },
    {
      "title": "New charging \u2018toaster\u2019 gadget gives your iPhone an instant battery boost so you never have to worry about charging again",
      "date": "2025-01-09 00:01:00",
      "generated_at": "2025-01-09 12:02:41",
      "meme_files": [
        "meme_20250109_120226_1.jpg",
        "meme_20250109_120227_2.jpg",
        "meme_20250109_120228_3.jpg",
        "meme_20250109_120229_4.jpg",
        "meme_20250109_120230_5.jpg",
        "meme_20250109_120231_6.jpg",
        "meme_20250109_120232_7.jpg",
        "meme_20250109_120233_8.jpg",
        "meme_20250109_120234_9.jpg",
        "meme_20250109_120235_10.jpg",
        "meme_20250109_120236_11.jpg",
        "meme_20250109_120237_12.jpg",
        "meme_20250109_120238_13.jpg",
        "meme_20250109_120239_14.jpg",
        "meme_20250109_120240_15.jpg",
        "meme_20250109_120241_16.jpg"
      ]
    },
    {
      "title": "Shutterstock Appoints Matt Furlong as Chief Marketplace Officer",
      "date": "2025-01-08 12:00:00",
      "generated_at": "2025-01-09 00:04:41",
      "meme_files": [
        "meme_20250109_000425_1.jpg",
        "meme_20250109_000426_2.jpg",
        "meme_20250109_000428_3.jpg",
        "meme_20250109_000429_4.jpg",
        "meme_20250109_000430_5.jpg",
        "meme_20250109_000431_6.jpg",
        "meme_20250109_000432_7.jpg",
        "meme_20250109_000433_8.jpg",
        "meme_20250109_000434_9.jpg",
        "meme_20250109_000435_10.jpg",
        "meme_20250109_000436_11.jpg",
        "meme_20250109_000437_12.jpg",
        "meme_20250109_000438_13.jpg",
        "meme_20250109_000439_14.jpg",
        "meme_20250109_000440_15.jpg",
        "meme_20250109_000441_16.jpg"
      ]
    },
    {
      "title": "Carbide Tools Market to exceed $17.3 Bn by 2032, Says Global Market Insights Inc.",
      "date": "2025-01-08 12:00:00",
      "generated_at": "2025-01-09 00:04:15",
      "meme_files": [
        "meme_20250109_000359_1.jpg",
        "meme_20250109_000400_2.jpg",
        "meme_20250109_000401_3.jpg",
        "meme_20250109_000402_4.jpg",
        "meme_20250109_000403_5.jpg",
        "meme_20250109_000404_6.jpg",
        "meme_20250109_000406_7.jpg",
        "meme_20250109_000407_8.jpg",
        "meme_20250109_000408_9.jpg",
        "meme_20250109_000409_10.jpg",
        "meme_20250109_000410_11.jpg",
        "meme_20250109_000411_12.jpg",
        "meme_20250109_000412_13.jpg",
        "meme_20250109_000413_14.jpg",
        "meme_20250109_000414_15.jpg",
        "meme_20250109_000415_16.jpg"
      ]
    },
    {
      "title": "AI in the retail industry is spreading beyond the IT department",
      "date": "2025-01-08 12:00:01",
      "generated_at": "2025-01-09 00:03:48",
      "meme_files": [
        "meme_20250109_000332_1.jpg",
        "meme_20250109_000333_2.jpg",
        "meme_20250109_000334_3.jpg",
        "meme_20250109_000335_4.jpg",
        "meme_20250109_000336_5.jpg",
        "meme_20250109_000337_6.jpg",
        "meme_20250109_000338_7.jpg",
        "meme_20250109_000340_8.jpg",
        "meme_20250109_000341_9.jpg",
        "meme_20250109_000342_10.jpg",
        "meme_20250109_000343_11.jpg",
        "meme_20250109_000344_12.jpg",
        "meme_20250109_000345_13.jpg",
        "meme_20250109_000346_14.jpg",
        "meme_20250109_000347_15.jpg",
        "meme_20250109_000348_16.jpg"
      ]
    },
    {
      "title": "Demystifying Autodesk: Insights From 20 Analyst Reviews",
      "date": "2025-01-08 12:00:58",
      "generated_at": "2025-01-09 00:03:21",
      "meme_files": [
        "meme_20250109_000305_1.jpg",
        "meme_20250109_000306_2.jpg",
        "meme_20250109_000307_3.jpg",
        "meme_20250109_000308_4.jpg",
        "meme_20250109_000309_5.jpg",
        "meme_20250109_000310_6.jpg",
        "meme_20250109_000311_7.jpg",
        "meme_20250109_000312_8.jpg",
        "meme_20250109_000313_9.jpg",
        "meme_20250109_000314_10.jpg",
        "meme_20250109_000315_11.jpg",
        "meme_20250109_000316_12.jpg",
        "meme_20250109_000317_13.jpg",
        "meme_20250109_000318_14.jpg",
        "meme_20250109_000320_15.jpg",
        "meme_20250109_000321_16.jpg"
      ]
    },
    {
      "title": "Progressive Web Apps Market Share to Rise at 31.0% CAGR, to Reach USD 22,069.45 Million by 2034 | PMR",
      "date": "2025-01-08 12:01:00",
      "generated_at": "2025-01-09 00:02:53",
      "meme_files": [
        "meme_20250109_000237_1.jpg",
        "meme_20250109_000238_2.jpg",
        "meme_20250109_000239_3.jpg",
        "meme_20250109_000240_4.jpg",
        "meme_20250109_000241_5.jpg",
        "meme_20250109_000242_6.jpg",
        "meme_20250109_000243_7.jpg",
        "meme_20250109_000245_8.jpg",
        "meme_20250109_000246_9.jpg",
        "meme_20250109_000247_10.jpg",
        "meme_20250109_000248_11.jpg",
        "meme_20250109_000249_12.jpg",
        "meme_20250109_000250_13.jpg",
        "meme_20250109_000251_14.jpg",
        "meme_20250109_000252_15.jpg",
        "meme_20250109_000253_16.jpg"
      ]
    },
    {
      "title": "Mariposa Labs Acheives Certifcation to ISO 22716, the Standard for Cosmetic Goods Manufacturing Practices",
      "date": "2025-01-07 23:57:00",
      "generated_at": "2025-01-08 12:04:21",
      "meme_files": [
        "meme_20250108_120406_1.jpg",
        "meme_20250108_120407_2.jpg",
        "meme_20250108_120408_3.jpg",
        "meme_20250108_120409_4.jpg",
        "meme_20250108_120410_5.jpg",
        "meme_20250108_120411_6.jpg",
        "meme_20250108_120412_7.jpg",
        "meme_20250108_120413_8.jpg",
        "meme_20250108_120414_9.jpg",
        "meme_20250108_120415_10.jpg",
        "meme_20250108_120416_11.jpg",
        "meme_20250108_120417_12.jpg",
        "meme_20250108_120418_13.jpg",
        "meme_20250108_120419_14.jpg",
        "meme_20250108_120420_15.jpg",
        "meme_20250108_120421_16.jpg"
      ]
    },
    {
      "title": "The Evolution of Digital Marketing and Jack Zuckowsky\u2019s Insights on Staying Ahead",
      "date": "2025-01-07 23:58:00",
      "generated_at": "2025-01-08 12:03:54",
      "meme_files": [
        "meme_20250108_120339_1.jpg",
        "meme_20250108_120339_2.jpg",
        "meme_20250108_120340_3.jpg",
        "meme_20250108_120341_4.jpg",
        "meme_20250108_120342_5.jpg",
        "meme_20250108_120344_6.jpg",
        "meme_20250108_120345_7.jpg",
        "meme_20250108_120346_8.jpg",
        "meme_20250108_120347_9.jpg",
        "meme_20250108_120348_10.jpg",
        "meme_20250108_120349_11.jpg",
        "meme_20250108_120350_12.jpg",
        "meme_20250108_120352_13.jpg",
        "meme_20250108_120352_14.jpg",
        "meme_20250108_120354_15.jpg",
        "meme_20250108_120354_16.jpg"
      ]
    },
    {
      "title": "Griffiss Institute adds new board members, advisers",
      "date": "2025-01-08 00:00:00",
      "generated_at": "2025-01-08 12:03:25",
      "meme_files": [
        "meme_20250108_120309_1.jpg",
        "meme_20250108_120310_2.jpg",
        "meme_20250108_120311_3.jpg",
        "meme_20250108_120312_4.jpg",
        "meme_20250108_120313_5.jpg",
        "meme_20250108_120314_6.jpg",
        "meme_20250108_120315_7.jpg",
        "meme_20250108_120316_8.jpg",
        "meme_20250108_120317_9.jpg",
        "meme_20250108_120318_10.jpg",
        "meme_20250108_120320_11.jpg",
        "meme_20250108_120321_12.jpg",
        "meme_20250108_120322_13.jpg",
        "meme_20250108_120323_14.jpg",
        "meme_20250108_120324_15.jpg",
        "meme_20250108_120325_16.jpg"
      ]
    },
    {
      "title": "The Key To a Hit Rap Song in 2025? Twitch Streamers",
      "date": "2025-01-08 00:00:00",
      "generated_at": "2025-01-08 12:02:57",
      "meme_files": [
        "meme_20250108_120241_1.jpg",
        "meme_20250108_120242_2.jpg",
        "meme_20250108_120243_3.jpg",
        "meme_20250108_120244_4.jpg",
        "meme_20250108_120245_5.jpg",
        "meme_20250108_120246_6.jpg",
        "meme_20250108_120247_7.jpg",
        "meme_20250108_120249_8.jpg",
        "meme_20250108_120250_9.jpg",
        "meme_20250108_120251_10.jpg",
        "meme_20250108_120252_11.jpg",
        "meme_20250108_120253_12.jpg",
        "meme_20250108_120254_13.jpg",
        "meme_20250108_120255_14.jpg",
        "meme_20250108_120256_15.jpg",
        "meme_20250108_120257_16.jpg"
      ]
    },
    {
      "title": "Toyota 'Exploring Rockets,' Kicks Off Inventor City: Automaker Ready To Take On Elon Musk",
      "date": "2025-01-08 00:01:35",
      "generated_at": "2025-01-08 12:02:29",
      "meme_files": [
        "meme_20250108_120212_1.jpg",
        "meme_20250108_120214_2.jpg",
        "meme_20250108_120214_3.jpg",
        "meme_20250108_120215_4.jpg",
        "meme_20250108_120216_5.jpg",
        "meme_20250108_120217_6.jpg",
        "meme_20250108_120219_7.jpg",
        "meme_20250108_120219_8.jpg",
        "meme_20250108_120221_9.jpg",
        "meme_20250108_120222_10.jpg",
        "meme_20250108_120223_11.jpg",
        "meme_20250108_120224_12.jpg",
        "meme_20250108_120225_13.jpg",
        "meme_20250108_120227_14.jpg",
        "meme_20250108_120228_15.jpg",
        "meme_20250108_120229_16.jpg"
      ]
    },
    {
      "title": "3 Cryptos to Make Multi-Millionaires Under a Crypto-Friendly SEC; Ripple on Top While Hedera and IntelMarkets Follow Demand",
      "date": "2025-01-07 12:00:36",
      "generated_at": "2025-01-08 00:05:20",
      "meme_files": [
        "meme_20250108_000457_1.jpg",
        "meme_20250108_000458_2.jpg",
        "meme_20250108_000459_3.jpg",
        "meme_20250108_000501_4.jpg",
        "meme_20250108_000503_5.jpg",
        "meme_20250108_000504_6.jpg",
        "meme_20250108_000506_7.jpg",
        "meme_20250108_000508_8.jpg",
        "meme_20250108_000509_9.jpg",
        "meme_20250108_000511_10.jpg",
        "meme_20250108_000513_11.jpg",
        "meme_20250108_000514_12.jpg",
        "meme_20250108_000516_13.jpg",
        "meme_20250108_000517_14.jpg",
        "meme_20250108_000519_15.jpg",
        "meme_20250108_000520_16.jpg"
      ]
    },
    {
      "title": "Robinhood Markets Stock: A Deep Dive Into Analyst Perspectives (27 Ratings)",
      "date": "2025-01-07 12:00:47",
      "generated_at": "2025-01-08 00:04:43",
      "meme_files": [
        "meme_20250108_000420_1.jpg",
        "meme_20250108_000422_2.jpg",
        "meme_20250108_000423_3.jpg",
        "meme_20250108_000425_4.jpg",
        "meme_20250108_000427_5.jpg",
        "meme_20250108_000428_6.jpg",
        "meme_20250108_000430_7.jpg",
        "meme_20250108_000431_8.jpg",
        "meme_20250108_000433_9.jpg",
        "meme_20250108_000434_10.jpg",
        "meme_20250108_000435_11.jpg",
        "meme_20250108_000437_12.jpg",
        "meme_20250108_000439_13.jpg",
        "meme_20250108_000440_14.jpg",
        "meme_20250108_000441_15.jpg",
        "meme_20250108_000443_16.jpg"
      ]
    },
    {
      "title": "Arteris, Inc. (NASDAQ:AIP) CEO K Charles Janac Sells 6,256 Shares",
      "date": "2025-01-07 12:00:50",
      "generated_at": "2025-01-08 00:04:07",
      "meme_files": [
        "meme_20250108_000345_1.jpg",
        "meme_20250108_000347_2.jpg",
        "meme_20250108_000348_3.jpg",
        "meme_20250108_000350_4.jpg",
        "meme_20250108_000351_5.jpg",
        "meme_20250108_000353_6.jpg",
        "meme_20250108_000355_7.jpg",
        "meme_20250108_000356_8.jpg",
        "meme_20250108_000358_9.jpg",
        "meme_20250108_000359_10.jpg",
        "meme_20250108_000401_11.jpg",
        "meme_20250108_000402_12.jpg",
        "meme_20250108_000403_13.jpg",
        "meme_20250108_000405_14.jpg",
        "meme_20250108_000406_15.jpg",
        "meme_20250108_000407_16.jpg"
      ]
    },
    {
      "title": "ONL Therapeutics Appoints Penny Fleck as Chief Development Officer",
      "date": "2025-01-07 12:00:52",
      "generated_at": "2025-01-08 00:03:32",
      "meme_files": [
        "meme_20250108_000310_1.jpg",
        "meme_20250108_000312_2.jpg",
        "meme_20250108_000313_3.jpg",
        "meme_20250108_000314_4.jpg",
        "meme_20250108_000316_5.jpg",
        "meme_20250108_000317_6.jpg",
        "meme_20250108_000319_7.jpg",
        "meme_20250108_000321_8.jpg",
        "meme_20250108_000322_9.jpg",
        "meme_20250108_000324_10.jpg",
        "meme_20250108_000325_11.jpg",
        "meme_20250108_000327_12.jpg",
        "meme_20250108_000328_13.jpg",
        "meme_20250108_000329_14.jpg",
        "meme_20250108_000331_15.jpg",
        "meme_20250108_000332_16.jpg"
      ]
    },
    {
      "title": "23 years ago, Apple launched one of the most beloved Macs of all time",
      "date": "2025-01-07 12:00:54",
      "generated_at": "2025-01-08 00:02:58",
      "meme_files": [
        "meme_20250108_000234_1.jpg",
        "meme_20250108_000236_2.jpg",
        "meme_20250108_000238_3.jpg",
        "meme_20250108_000239_4.jpg",
        "meme_20250108_000241_5.jpg",
        "meme_20250108_000242_6.jpg",
        "meme_20250108_000244_7.jpg",
        "meme_20250108_000245_8.jpg",
        "meme_20250108_000247_9.jpg",
        "meme_20250108_000248_10.jpg",
        "meme_20250108_000250_11.jpg",
        "meme_20250108_000251_12.jpg",
        "meme_20250108_000253_13.jpg",
        "meme_20250108_000254_14.jpg",
        "meme_20250108_000256_15.jpg",
        "meme_20250108_000258_16.jpg"
      ]
    },
    {
      "title": "The Groundbreaking Lucid Gravity to Leverage Panasonic Energy's Latest-Generation High-Performance EV Batteries",
      "date": "2025-01-07 00:00:00",
      "generated_at": "2025-01-07 12:04:48",
      "meme_files": [
        "meme_20250107_120425_1.jpg",
        "meme_20250107_120427_2.jpg",
        "meme_20250107_120428_3.jpg",
        "meme_20250107_120429_4.jpg",
        "meme_20250107_120431_5.jpg",
        "meme_20250107_120433_6.jpg",
        "meme_20250107_120434_7.jpg",
        "meme_20250107_120436_8.jpg",
        "meme_20250107_120438_9.jpg",
        "meme_20250107_120439_10.jpg",
        "meme_20250107_120441_11.jpg",
        "meme_20250107_120442_12.jpg",
        "meme_20250107_120444_13.jpg",
        "meme_20250107_120445_14.jpg",
        "meme_20250107_120446_15.jpg",
        "meme_20250107_120448_16.jpg"
      ]
    },
    {
      "title": "Scientists document the secret language of sperm whales",
      "date": "2025-01-07 00:00:03",
      "generated_at": "2025-01-07 12:04:13",
      "meme_files": [
        "meme_20250107_120349_1.jpg",
        "meme_20250107_120351_2.jpg",
        "meme_20250107_120352_3.jpg",
        "meme_20250107_120353_4.jpg",
        "meme_20250107_120355_5.jpg",
        "meme_20250107_120357_6.jpg",
        "meme_20250107_120358_7.jpg",
        "meme_20250107_120400_8.jpg",
        "meme_20250107_120401_9.jpg",
        "meme_20250107_120403_10.jpg",
        "meme_20250107_120405_11.jpg",
        "meme_20250107_120407_12.jpg",
        "meme_20250107_120408_13.jpg",
        "meme_20250107_120410_14.jpg",
        "meme_20250107_120411_15.jpg",
        "meme_20250107_120413_16.jpg"
      ]
    },
    {
      "title": "Digital Monitoring is No Substitute for Engaged Management for Remote Work Success",
      "date": "2025-01-07 00:00:29",
      "generated_at": "2025-01-07 12:03:27",
      "meme_files": [
        "meme_20250107_120303_1.jpg",
        "meme_20250107_120304_2.jpg",
        "meme_20250107_120306_3.jpg",
        "meme_20250107_120307_4.jpg",
        "meme_20250107_120309_5.jpg",
        "meme_20250107_120311_6.jpg",
        "meme_20250107_120313_7.jpg",
        "meme_20250107_120314_8.jpg",
        "meme_20250107_120316_9.jpg",
        "meme_20250107_120318_10.jpg",
        "meme_20250107_120319_11.jpg",
        "meme_20250107_120321_12.jpg",
        "meme_20250107_120323_13.jpg",
        "meme_20250107_120324_14.jpg",
        "meme_20250107_120326_15.jpg",
        "meme_20250107_120327_16.jpg"
      ]
    },
    {
      "title": "Crucial \u2018golden quarter\u2019 fails to save 2024 for retailers",
      "date": "2025-01-07 00:01:00",
      "generated_at": "2025-01-07 12:02:49",
      "meme_files": [
        "meme_20250107_120225_1.jpg",
        "meme_20250107_120227_2.jpg",
        "meme_20250107_120229_3.jpg",
        "meme_20250107_120230_4.jpg",
        "meme_20250107_120232_5.jpg",
        "meme_20250107_120233_6.jpg",
        "meme_20250107_120235_7.jpg",
        "meme_20250107_120236_8.jpg",
        "meme_20250107_120238_9.jpg",
        "meme_20250107_120239_10.jpg",
        "meme_20250107_120241_11.jpg",
        "meme_20250107_120243_12.jpg",
        "meme_20250107_120244_13.jpg",
        "meme_20250107_120246_14.jpg",
        "meme_20250107_120248_15.jpg",
        "meme_20250107_120249_16.jpg"
      ]
    },
    {
      "title": "37 Analysts Assess Fortinet: What You Need To Know",
      "date": "2025-01-06 12:00:43",
      "generated_at": "2025-01-07 00:05:46",
      "meme_files": [
        "meme_20250107_000523_1.jpg",
        "meme_20250107_000524_2.jpg",
        "meme_20250107_000526_3.jpg",
        "meme_20250107_000527_4.jpg",
        "meme_20250107_000529_5.jpg",
        "meme_20250107_000531_6.jpg",
        "meme_20250107_000532_7.jpg",
        "meme_20250107_000534_8.jpg",
        "meme_20250107_000535_9.jpg",
        "meme_20250107_000536_10.jpg",
        "meme_20250107_000538_11.jpg",
        "meme_20250107_000539_12.jpg",
        "meme_20250107_000541_13.jpg",
        "meme_20250107_000543_14.jpg",
        "meme_20250107_000544_15.jpg",
        "meme_20250107_000546_16.jpg"
      ]
    },
    {
      "title": "Mullen Automotive (NASDAQ:MULN) versus Oshkosh (NYSE:OSK) Head-To-Head Analysis",
      "date": "2025-01-06 12:00:49",
      "generated_at": "2025-01-07 00:05:11",
      "meme_files": [
        "meme_20250107_000447_1.jpg",
        "meme_20250107_000449_2.jpg",
        "meme_20250107_000451_3.jpg",
        "meme_20250107_000452_4.jpg",
        "meme_20250107_000454_5.jpg",
        "meme_20250107_000455_6.jpg",
        "meme_20250107_000457_7.jpg",
        "meme_20250107_000458_8.jpg",
        "meme_20250107_000500_9.jpg",
        "meme_20250107_000501_10.jpg",
        "meme_20250107_000503_11.jpg",
        "meme_20250107_000504_12.jpg",
        "meme_20250107_000506_13.jpg",
        "meme_20250107_000507_14.jpg",
        "meme_20250107_000509_15.jpg",
        "meme_20250107_000511_16.jpg"
      ]
    },
    {
      "title": "ProAssurance (NYSE:PRA) vs. Skyward Specialty Insurance Group (NASDAQ:SKWD) Head-To-Head Review",
      "date": "2025-01-06 12:00:49",
      "generated_at": "2025-01-07 00:04:34",
      "meme_files": [
        "meme_20250107_000410_1.jpg",
        "meme_20250107_000412_2.jpg",
        "meme_20250107_000414_3.jpg",
        "meme_20250107_000415_4.jpg",
        "meme_20250107_000417_5.jpg",
        "meme_20250107_000419_6.jpg",
        "meme_20250107_000420_7.jpg",
        "meme_20250107_000422_8.jpg",
        "meme_20250107_000423_9.jpg",
        "meme_20250107_000425_10.jpg",
        "meme_20250107_000426_11.jpg",
        "meme_20250107_000428_12.jpg",
        "meme_20250107_000429_13.jpg",
        "meme_20250107_000431_14.jpg",
        "meme_20250107_000432_15.jpg",
        "meme_20250107_000434_16.jpg"
      ]
    },
    {
      "title": "The Analyst Verdict: Advanced Energy Indus In The Eyes Of 7 Experts",
      "date": "2025-01-06 12:00:50",
      "generated_at": "2025-01-07 00:03:50",
      "meme_files": [
        "meme_20250107_000327_1.jpg",
        "meme_20250107_000329_2.jpg",
        "meme_20250107_000331_3.jpg",
        "meme_20250107_000332_4.jpg",
        "meme_20250107_000334_5.jpg",
        "meme_20250107_000335_6.jpg",
        "meme_20250107_000337_7.jpg",
        "meme_20250107_000338_8.jpg",
        "meme_20250107_000340_9.jpg",
        "meme_20250107_000341_10.jpg",
        "meme_20250107_000343_11.jpg",
        "meme_20250107_000344_12.jpg",
        "meme_20250107_000346_13.jpg",
        "meme_20250107_000347_14.jpg",
        "meme_20250107_000349_15.jpg",
        "meme_20250107_000350_16.jpg"
      ]
    },
    {
      "title": "i2Cool Powers Green Event Management at Hong Kong Coliseum with Electricity-free Cooling Technology",
      "date": "2025-01-06 12:01:00",
      "generated_at": "2025-01-07 00:03:14",
      "meme_files": [
        "meme_20250107_000251_1.jpg",
        "meme_20250107_000252_2.jpg",
        "meme_20250107_000254_3.jpg",
        "meme_20250107_000255_4.jpg",
        "meme_20250107_000257_5.jpg",
        "meme_20250107_000259_6.jpg",
        "meme_20250107_000300_7.jpg",
        "meme_20250107_000302_8.jpg",
        "meme_20250107_000304_9.jpg",
        "meme_20250107_000305_10.jpg",
        "meme_20250107_000306_11.jpg",
        "meme_20250107_000308_12.jpg",
        "meme_20250107_000310_13.jpg",
        "meme_20250107_000311_14.jpg",
        "meme_20250107_000312_15.jpg",
        "meme_20250107_000314_16.jpg"
      ]
    },
    {
      "title": "Nvidia GeForce RTX 5090 Revealed And It\u2019s Massive",
      "date": "2025-01-05 23:31:02",
      "generated_at": "2025-01-06 12:04:17",
      "meme_files": [
        "meme_20250106_120402_1.jpg",
        "meme_20250106_120403_2.jpg",
        "meme_20250106_120404_3.jpg",
        "meme_20250106_120405_4.jpg",
        "meme_20250106_120406_5.jpg",
        "meme_20250106_120407_6.jpg",
        "meme_20250106_120408_7.jpg",
        "meme_20250106_120409_8.jpg",
        "meme_20250106_120410_9.jpg",
        "meme_20250106_120411_10.jpg",
        "meme_20250106_120412_11.jpg",
        "meme_20250106_120413_12.jpg",
        "meme_20250106_120414_13.jpg",
        "meme_20250106_120415_14.jpg",
        "meme_20250106_120416_15.jpg",
        "meme_20250106_120417_16.jpg"
      ]
    },
    {
      "title": "Samsung Galaxy S24 Users About To Get A New Free Upgrade, Report Claims",
      "date": "2025-01-05 23:40:02",
      "generated_at": "2025-01-06 12:03:51",
      "meme_files": [
        "meme_20250106_120335_1.jpg",
        "meme_20250106_120336_2.jpg",
        "meme_20250106_120337_3.jpg",
        "meme_20250106_120338_4.jpg",
        "meme_20250106_120340_5.jpg",
        "meme_20250106_120341_6.jpg",
        "meme_20250106_120342_7.jpg",
        "meme_20250106_120343_8.jpg",
        "meme_20250106_120344_9.jpg",
        "meme_20250106_120344_10.jpg",
        "meme_20250106_120345_11.jpg",
        "meme_20250106_120346_12.jpg",
        "meme_20250106_120348_13.jpg",
        "meme_20250106_120349_14.jpg",
        "meme_20250106_120350_15.jpg",
        "meme_20250106_120351_16.jpg"
      ]
    },
    {
      "title": "Govee Partners with IDC to Discuss the Impact of Smart Lighting and the Future of Smart Living In a New Whitepaper",
      "date": "2025-01-05 23:50:13",
      "generated_at": "2025-01-06 12:03:20",
      "meme_files": [
        "meme_20250106_120305_1.jpg",
        "meme_20250106_120306_2.jpg",
        "meme_20250106_120307_3.jpg",
        "meme_20250106_120308_4.jpg",
        "meme_20250106_120309_5.jpg",
        "meme_20250106_120310_6.jpg",
        "meme_20250106_120311_7.jpg",
        "meme_20250106_120312_8.jpg",
        "meme_20250106_120313_9.jpg",
        "meme_20250106_120314_10.jpg",
        "meme_20250106_120315_11.jpg",
        "meme_20250106_120316_12.jpg",
        "meme_20250106_120317_13.jpg",
        "meme_20250106_120318_14.jpg",
        "meme_20250106_120319_15.jpg",
        "meme_20250106_120320_16.jpg"
      ]
    },
    {
      "title": "Shield your drinking water from microplastics via boiling",
      "date": "2025-01-06 00:00:38",
      "generated_at": "2025-01-06 12:02:20",
      "meme_files": [
        "meme_20250106_120204_1.jpg",
        "meme_20250106_120205_2.jpg",
        "meme_20250106_120206_3.jpg",
        "meme_20250106_120207_4.jpg",
        "meme_20250106_120208_5.jpg",
        "meme_20250106_120209_6.jpg",
        "meme_20250106_120210_7.jpg",
        "meme_20250106_120211_8.jpg",
        "meme_20250106_120212_9.jpg",
        "meme_20250106_120213_10.jpg",
        "meme_20250106_120214_11.jpg",
        "meme_20250106_120215_12.jpg",
        "meme_20250106_120216_13.jpg",
        "meme_20250106_120217_14.jpg",
        "meme_20250106_120218_15.jpg",
        "meme_20250106_120220_16.jpg"
      ]
    },
    {
      "title": "NexOptic Technology (CVE:NXO) Trading 50% Higher \u2013 Should You Buy?",
      "date": "2025-01-05 12:01:29",
      "generated_at": "2025-01-06 00:05:41",
      "meme_files": [
        "meme_20250106_000518_1.jpg",
        "meme_20250106_000520_2.jpg",
        "meme_20250106_000521_3.jpg",
        "meme_20250106_000522_4.jpg",
        "meme_20250106_000524_5.jpg",
        "meme_20250106_000526_6.jpg",
        "meme_20250106_000527_7.jpg",
        "meme_20250106_000529_8.jpg",
        "meme_20250106_000530_9.jpg",
        "meme_20250106_000532_10.jpg",
        "meme_20250106_000533_11.jpg",
        "meme_20250106_000535_12.jpg",
        "meme_20250106_000536_13.jpg",
        "meme_20250106_000538_14.jpg",
        "meme_20250106_000540_15.jpg",
        "meme_20250106_000541_16.jpg"
      ]
    },
    {
      "title": "BCE (NYSE:BCE) Stock Price Up 1% \u2013 Should You Buy?",
      "date": "2025-01-05 12:01:30",
      "generated_at": "2025-01-06 00:05:07",
      "meme_files": [
        "meme_20250106_000443_1.jpg",
        "meme_20250106_000445_2.jpg",
        "meme_20250106_000447_3.jpg",
        "meme_20250106_000449_4.jpg",
        "meme_20250106_000450_5.jpg",
        "meme_20250106_000452_6.jpg",
        "meme_20250106_000453_7.jpg",
        "meme_20250106_000455_8.jpg",
        "meme_20250106_000457_9.jpg",
        "meme_20250106_000458_10.jpg",
        "meme_20250106_000500_11.jpg",
        "meme_20250106_000501_12.jpg",
        "meme_20250106_000503_13.jpg",
        "meme_20250106_000504_14.jpg",
        "meme_20250106_000506_15.jpg",
        "meme_20250106_000507_16.jpg"
      ]
    },
    {
      "title": "PayPal (NASDAQ:PYPL) Trading Up 0.9% \u2013 Here\u2019s Why",
      "date": "2025-01-05 12:01:30",
      "generated_at": "2025-01-06 00:04:30",
      "meme_files": [
        "meme_20250106_000408_1.jpg",
        "meme_20250106_000409_2.jpg",
        "meme_20250106_000411_3.jpg",
        "meme_20250106_000413_4.jpg",
        "meme_20250106_000414_5.jpg",
        "meme_20250106_000416_6.jpg",
        "meme_20250106_000417_7.jpg",
        "meme_20250106_000419_8.jpg",
        "meme_20250106_000421_9.jpg",
        "meme_20250106_000422_10.jpg",
        "meme_20250106_000423_11.jpg",
        "meme_20250106_000425_12.jpg",
        "meme_20250106_000426_13.jpg",
        "meme_20250106_000428_14.jpg",
        "meme_20250106_000429_15.jpg",
        "meme_20250106_000430_16.jpg"
      ]
    },
    {
      "title": "SoFi Technologies (NASDAQ:SOFI) Trading Up 2.1% \u2013 Still a Buy?",
      "date": "2025-01-05 12:01:31",
      "generated_at": "2025-01-06 00:03:57",
      "meme_files": [
        "meme_20250106_000334_1.jpg",
        "meme_20250106_000335_2.jpg",
        "meme_20250106_000337_3.jpg",
        "meme_20250106_000339_4.jpg",
        "meme_20250106_000340_5.jpg",
        "meme_20250106_000341_6.jpg",
        "meme_20250106_000343_7.jpg",
        "meme_20250106_000344_8.jpg",
        "meme_20250106_000345_9.jpg",
        "meme_20250106_000347_10.jpg",
        "meme_20250106_000348_11.jpg",
        "meme_20250106_000350_12.jpg",
        "meme_20250106_000352_13.jpg",
        "meme_20250106_000353_14.jpg",
        "meme_20250106_000355_15.jpg",
        "meme_20250106_000357_16.jpg"
      ]
    },
    {
      "title": "Mincey, Brooks put up 16 in UMass-Lowell's 73-69 victory against Albany to open American East action",
      "date": "2025-01-04 23:57:42",
      "generated_at": "2025-01-05 12:05:01",
      "meme_files": [
        "meme_20250105_120441_1.jpg",
        "meme_20250105_120442_2.jpg",
        "meme_20250105_120444_3.jpg",
        "meme_20250105_120445_4.jpg",
        "meme_20250105_120446_5.jpg",
        "meme_20250105_120447_6.jpg",
        "meme_20250105_120448_7.jpg",
        "meme_20250105_120450_8.jpg",
        "meme_20250105_120451_9.jpg",
        "meme_20250105_120453_10.jpg",
        "meme_20250105_120454_11.jpg",
        "meme_20250105_120456_12.jpg",
        "meme_20250105_120457_13.jpg",
        "meme_20250105_120459_14.jpg",
        "meme_20250105_120500_15.jpg",
        "meme_20250105_120501_16.jpg"
      ]
    },
    {
      "title": "VF Developments, LLC Breathes New Life into \"The Grove\" a 1960s Era Mid Century Modern Apartment Community Featuring Three Bedroom Rental Homes Near USC & Downtown Los Angeles",
      "date": "2025-01-04 23:59:00",
      "generated_at": "2025-01-05 12:04:30",
      "meme_files": [
        "meme_20250105_120407_1.jpg",
        "meme_20250105_120409_2.jpg",
        "meme_20250105_120410_3.jpg",
        "meme_20250105_120412_4.jpg",
        "meme_20250105_120413_5.jpg",
        "meme_20250105_120415_6.jpg",
        "meme_20250105_120416_7.jpg",
        "meme_20250105_120418_8.jpg",
        "meme_20250105_120419_9.jpg",
        "meme_20250105_120420_10.jpg",
        "meme_20250105_120422_11.jpg",
        "meme_20250105_120423_12.jpg",
        "meme_20250105_120425_13.jpg",
        "meme_20250105_120426_14.jpg",
        "meme_20250105_120428_15.jpg",
        "meme_20250105_120430_16.jpg"
      ]
    },
    {
      "title": "Eni Launches Europe\u2019s Most Powerful Supercomputer",
      "date": "2025-01-05 00:00:00",
      "generated_at": "2025-01-05 12:03:57",
      "meme_files": [
        "meme_20250105_120333_1.jpg",
        "meme_20250105_120335_2.jpg",
        "meme_20250105_120336_3.jpg",
        "meme_20250105_120338_4.jpg",
        "meme_20250105_120340_5.jpg",
        "meme_20250105_120341_6.jpg",
        "meme_20250105_120343_7.jpg",
        "meme_20250105_120344_8.jpg",
        "meme_20250105_120347_9.jpg",
        "meme_20250105_120348_10.jpg",
        "meme_20250105_120350_11.jpg",
        "meme_20250105_120351_12.jpg",
        "meme_20250105_120353_13.jpg",
        "meme_20250105_120354_14.jpg",
        "meme_20250105_120355_15.jpg",
        "meme_20250105_120357_16.jpg"
      ]
    },
    {
      "title": "AI, car tech and \u2018weird\u2019 gadgets expected to dominate at CES trade show",
      "date": "2025-01-05 00:01:00",
      "generated_at": "2025-01-05 12:02:14",
      "meme_files": [
        "meme_20250105_120151_1.jpg",
        "meme_20250105_120153_2.jpg",
        "meme_20250105_120154_3.jpg",
        "meme_20250105_120156_4.jpg",
        "meme_20250105_120157_5.jpg",
        "meme_20250105_120159_6.jpg",
        "meme_20250105_120200_7.jpg",
        "meme_20250105_120202_8.jpg",
        "meme_20250105_120203_9.jpg",
        "meme_20250105_120205_10.jpg",
        "meme_20250105_120207_11.jpg",
        "meme_20250105_120208_12.jpg",
        "meme_20250105_120210_13.jpg",
        "meme_20250105_120211_14.jpg",
        "meme_20250105_120213_15.jpg",
        "meme_20250105_120214_16.jpg"
      ]
    },
    {
      "title": "Vaxcyte (NASDAQ:PCVX) and CRISPR Therapeutics (NASDAQ:CRSP) Head to Head Comparison",
      "date": "2025-01-04 11:50:50",
      "generated_at": "2025-01-05 00:04:42",
      "meme_files": [
        "meme_20250105_000426_1.jpg",
        "meme_20250105_000427_2.jpg",
        "meme_20250105_000428_3.jpg",
        "meme_20250105_000430_4.jpg",
        "meme_20250105_000431_5.jpg",
        "meme_20250105_000432_6.jpg",
        "meme_20250105_000433_7.jpg",
        "meme_20250105_000434_8.jpg",
        "meme_20250105_000435_9.jpg",
        "meme_20250105_000436_10.jpg",
        "meme_20250105_000437_11.jpg",
        "meme_20250105_000438_12.jpg",
        "meme_20250105_000439_13.jpg",
        "meme_20250105_000440_14.jpg",
        "meme_20250105_000441_15.jpg",
        "meme_20250105_000442_16.jpg"
      ]
    },
    {
      "title": "Just Like Clockwork, The Propaganda Push For Digital ID Kicks Into Gear In The UK",
      "date": "2025-01-04 12:00:00",
      "generated_at": "2025-01-05 00:04:15",
      "meme_files": [
        "meme_20250105_000359_1.jpg",
        "meme_20250105_000400_2.jpg",
        "meme_20250105_000401_3.jpg",
        "meme_20250105_000402_4.jpg",
        "meme_20250105_000403_5.jpg",
        "meme_20250105_000404_6.jpg",
        "meme_20250105_000405_7.jpg",
        "meme_20250105_000406_8.jpg",
        "meme_20250105_000407_9.jpg",
        "meme_20250105_000408_10.jpg",
        "meme_20250105_000409_11.jpg",
        "meme_20250105_000411_12.jpg",
        "meme_20250105_000412_13.jpg",
        "meme_20250105_000413_14.jpg",
        "meme_20250105_000414_15.jpg",
        "meme_20250105_000415_16.jpg"
      ]
    },
    {
      "title": "Stuck With One Internet Provider? The Secret Behind Internet Monopolies",
      "date": "2025-01-04 12:00:00",
      "generated_at": "2025-01-05 00:02:39",
      "meme_files": [
        "meme_20250105_000223_1.jpg",
        "meme_20250105_000224_2.jpg",
        "meme_20250105_000225_3.jpg",
        "meme_20250105_000226_4.jpg",
        "meme_20250105_000227_5.jpg",
        "meme_20250105_000228_6.jpg",
        "meme_20250105_000229_7.jpg",
        "meme_20250105_000230_8.jpg",
        "meme_20250105_000231_9.jpg",
        "meme_20250105_000232_10.jpg",
        "meme_20250105_000234_11.jpg",
        "meme_20250105_000234_12.jpg",
        "meme_20250105_000235_13.jpg",
        "meme_20250105_000236_14.jpg",
        "meme_20250105_000238_15.jpg",
        "meme_20250105_000239_16.jpg"
      ]
    },
    {
      "title": "Bob Dylan has some Dylanesque thoughts on the \u201csorcery\u201d of technology",
      "date": "2025-01-04 12:00:34",
      "generated_at": "2025-01-05 00:02:12",
      "meme_files": [
        "meme_20250105_000156_1.jpg",
        "meme_20250105_000157_2.jpg",
        "meme_20250105_000158_3.jpg",
        "meme_20250105_000200_4.jpg",
        "meme_20250105_000201_5.jpg",
        "meme_20250105_000202_6.jpg",
        "meme_20250105_000203_7.jpg",
        "meme_20250105_000204_8.jpg",
        "meme_20250105_000205_9.jpg",
        "meme_20250105_000206_10.jpg",
        "meme_20250105_000207_11.jpg",
        "meme_20250105_000208_12.jpg",
        "meme_20250105_000209_13.jpg",
        "meme_20250105_000210_14.jpg",
        "meme_20250105_000211_15.jpg",
        "meme_20250105_000212_16.jpg"
      ]
    },
    {
      "title": "TikTok Knew Livestreams Exploited Minors, Suit Claims",
      "date": "2025-01-03 23:34:50",
      "generated_at": "2025-01-04 12:04:26",
      "meme_files": [
        "meme_20250104_120411_1.jpg",
        "meme_20250104_120412_2.jpg",
        "meme_20250104_120414_3.jpg",
        "meme_20250104_120414_4.jpg",
        "meme_20250104_120416_5.jpg",
        "meme_20250104_120417_6.jpg",
        "meme_20250104_120417_7.jpg",
        "meme_20250104_120418_8.jpg",
        "meme_20250104_120419_9.jpg",
        "meme_20250104_120420_10.jpg",
        "meme_20250104_120421_11.jpg",
        "meme_20250104_120422_12.jpg",
        "meme_20250104_120423_13.jpg",
        "meme_20250104_120424_14.jpg",
        "meme_20250104_120425_15.jpg",
        "meme_20250104_120426_16.jpg"
      ]
    }
  ]
}